{
    "name": "python3-numpy",
    "buildsystem": "simple",
    "build-commands": [
        "pip3 install --no-build-isolation --exists-action=i --no-index --find-links=\"file://${PWD}\" --prefix=${FLATPAK_DEST} \"numpy\""
    ],
    "sources": [
        {
            "type": "file",
            "url": "https://files.pythonhosted.org/packages/c5/63/a48648ebc57711348420670bb074998f79828291f68aebfff1642be212ec/numpy-1.19.4.zip",
            "sha256": "141ec3a3300ab89c7f2b0775289954d193cc8edb621ea05f99db9cb181530512"
        }
    ]
}
